base2base/__init__.py
base2base/converter.py
base2base-0.1.0.dist-info/METADATA
base2base-0.1.0.dist-info/WHEEL
base2base-0.1.0.dist-info/top_level.txt
base2base-0.1.0.dist-info/RECORD
